ehelply_microservice_library/__init__.py
ehelply_microservice_library/cli/__init__.py
ehelply_microservice_library/cli/cli_aws.py
ehelply_microservice_library/cli/cli_cryptography.py
ehelply_microservice_library/cli/cli_database.py
ehelply_microservice_library/cli/cli_release.py
ehelply_microservice_library/cli/cli_service.py
ehelply_microservice_library/cli/cli_state.py
ehelply_microservice_library/cli/cli_test.py
ehelply_microservice_library/cli/cli_update.py
ehelply_microservice_library/cli/cli_utils.py
ehelply_microservice_library/cli/clis.py
ehelply_microservice_library/cli/self_cli.py
ehelply_microservice_library/integrations/__init__.py
ehelply_microservice_library/integrations/fact.py
ehelply_microservice_library/integrations/logging.py
ehelply_microservice_library/integrations/m2m.py
ehelply_microservice_library/integrations/monitor.py
ehelply_microservice_library/integrations/notifications.py
ehelply_microservice_library/integrations/router_integrations.py
ehelply_microservice_library/integrations/sdk.py
ehelply_microservice_library/integrations/ueri.py
ehelply_microservice_library/lightweight_bootstrap.py
ehelply_microservice_library/realtime/__init__.py
ehelply_microservice_library/realtime/initializers.py
ehelply_microservice_library/routers/__init__.py
ehelply_microservice_library/routers/router_service.py
ehelply_microservice_library/routers/router_service_meta.py
ehelply_microservice_library/routers/router_service_monitor.py
ehelply_microservice_library/routers/router_service_security.py
ehelply_microservice_library/service_bootstrap.py
ehelply_microservice_library/utils/__init__.py
ehelply_microservice_library/utils/constants/__init__.py
ehelply_microservice_library/utils/constants/constants_gatekeeper.py
ehelply_microservice_library/utils/constants/constants_time.py
ehelply_microservice_library/utils/ehelply_cloud.py
ehelply_microservice_library/utils/exceptions.py
ehelply_microservice_library/utils/manager_base.py
ehelply_microservice_library-1.12.3.dist-info/entry_points.txt
ehelply_microservice_library-1.12.3.dist-info/WHEEL
ehelply_microservice_library-1.12.3.dist-info/METADATA
ehelply_microservice_library-1.12.3.dist-info/RECORD
